yarp_parser/__init__.py
yarp_parser/recursive_parser.py
yarp_parser/streaming_lexer.py
yarp_parser-0.2.dist-info/LICENSE
yarp_parser-0.2.dist-info/METADATA
yarp_parser-0.2.dist-info/WHEEL
yarp_parser-0.2.dist-info/top_level.txt
yarp_parser-0.2.dist-info/RECORD
