Metadata-Version: 2.1
Name: yarp-parser
Version: 0.2
Summary: YARP - Yet Another Recursive Parser.
Home-page: https://github.com/ewimberley/yarp
Author: Eric Wimberley
License: UNKNOWN
Project-URL: Bug Tracker, https://github.com/ewimberley/yarp/issues
Platform: UNKNOWN
Requires-Python: >=3.6
License-File: LICENSE
